{
  "JA1": "最嚴謹比對",
  "JA2": "排除鄰比對",
  "JA3": "排除村、里比對",
  "JB1": "退室比對",
  "JB2": "樓之之樓比對",
  "JB3": "退樓後之比對",
  "JB4": "退樓比對",
  "JB5": "號之之號比對",
  "JC1": "臨建特附進階比對",
  "JC2": "路地名進階比對",
  "JC3": "缺路地名進階比對",
  "JC4": "號樓之要件進階比對",
  "JD1": "排除要件對應多址",
  "JD2": "地址明確拆分多址",
  "JD3": "退室多址比對",
  "JD4": "退樓後之多址比對",
  "JD5": "退樓多址比對",
  "JD6": "附近地址比對",
  "JD7": "增編多址比對",
  "JE1": "公設",
  "JE2": "具方向性地址",
  "JE3": "特殊地址",
  "JE4": "地址要件不齊",
  "JE5": "地址不存在母體",
  "JE61": "門牌廢止",
  "JE62": "異動軌跡有異",
  "JE9": "其他"
}
